setup.cfg
setup.py
buffer/__init__.py
buffer/client.py
buffer/api/__init__.py
buffer/api/info.py
buffer/api/link.py
buffer/api/profile.py
buffer/api/schedule.py
buffer/api/update.py
buffer/api/user.py
buffer/error/__init__.py
buffer/error/client_error.py
buffer/http_client/__init__.py
buffer/http_client/auth_handler.py
buffer/http_client/error_handler.py
buffer/http_client/request_handler.py
buffer/http_client/response.py
buffer/http_client/response_handler.py
buffer_api.egg-info/PKG-INFO
buffer_api.egg-info/SOURCES.txt
buffer_api.egg-info/dependency_links.txt
buffer_api.egg-info/requires.txt
buffer_api.egg-info/top_level.txt