Metadata-Version: 1.1
Name: buffer-api
Version: 0.2.5
Summary: Buffer API library client for python
Home-page: https://github.com/barisariburnu/buffer-api
Author: barisariburnu
Author-email: barisariburnu@gmail.com
License: GNU GENERAL PUBLIC LICENSE
Download-URL: https://github.com/barisariburnu/buffer-api/releases/tag/0.2.5
Keywords: Buffer API library client for python
Platform: UNKNOWN
Classifier: Development Status :: 5 - Production/Stable
Classifier: Intended Audience :: Developers
Classifier: License :: OSI Approved :: MIT License
Classifier: Operating System :: OS Independent
Classifier: Programming Language :: Python :: 2.6
Classifier: Programming Language :: Python :: 2.7
Classifier: Programming Language :: Python :: 3.2
Classifier: Programming Language :: Python :: 3.3
Classifier: Topic :: Software Development :: Libraries :: Python Modules
